VolSplinesLib/__init__.py
VolSplinesLib/interpolation_function.py
VolSplinesLib/interpolations.py
VolSplinesLib/minimize.py
VolSplinesLib-0.1.3.dist-info/LICENSE
VolSplinesLib-0.1.3.dist-info/METADATA
VolSplinesLib-0.1.3.dist-info/WHEEL
VolSplinesLib-0.1.3.dist-info/top_level.txt
VolSplinesLib-0.1.3.dist-info/RECORD
