Metadata-Version: 2.1
Name: VolSplinesLib
Version: 0.1.3
Summary: A library for interpolating implied volatility surfaces
Home-page: https://github.com/hedge0/VolSplinesLib
Author: hedge0
Classifier: Programming Language :: Python :: 3
Classifier: License :: OSI Approved :: MIT License
Classifier: Operating System :: OS Independent
Requires-Python: >=3.6
License-File: LICENSE
Requires-Dist: numpy
